pulse_aws/__init__.py
pulse_aws/baseline.py
pulse_aws/cdk/__init__.py
pulse_aws/cdk/app.py
pulse_aws/cdk/baseline.py
pulse_aws/cdk/cdk.json
pulse_aws/cdk/helpers.py
pulse_aws/certificate.py
pulse_aws/cli.py
pulse_aws/config.py
pulse_aws/deployment.py
pulse_aws/plugin.py
pulse_aws/py.typed
pulse_aws/reaper_lambda.py
pulse_aws/reporting.py
pulse_aws/teardown.py
pulse_aws-0.1.9.dist-info/WHEEL
pulse_aws-0.1.9.dist-info/entry_points.txt
pulse_aws-0.1.9.dist-info/METADATA
pulse_aws-0.1.9.dist-info/RECORD
