Metadata-Version: 2.3
Name: pulse-aws
Version: 0.1.9
Summary: Add your description here
Author: Erwin Kuhn
Author-email: Erwin Kuhn <erwin.kuhn@protonmail.com>
Requires-Dist: aws-cdk-lib>=2.160.0,<3.0
Requires-Dist: constructs>=10.0.0,<11.0.0
Requires-Dist: boto3>=1.35.0,<2.0.0
Requires-Dist: botocore>=1.35.0,<2.0.0
Requires-Dist: httpx>=0.27.0,<1.0.0
Requires-Dist: requests>=2.32.5
Requires-Python: >=3.11
